chuk_virtual_shell-0.1.7.dist-info/METADATA
chuk_virtual_shell-0.1.7.dist-info/WHEEL
chuk_virtual_shell-0.1.7.dist-info/entry_points.txt
chuk_virtual_shell/__init__.py
chuk_virtual_shell/cli/sandbox-cli.md
chuk_virtual_shell/cli/sandbox_cli.py
chuk_virtual_shell/cli/sandbox_manager_cli.py
chuk_virtual_shell/commands/__init__.py
chuk_virtual_shell/commands/command_base.py
chuk_virtual_shell/commands/command_loader.py
chuk_virtual_shell/commands/environment/README.md
chuk_virtual_shell/commands/environment/__init__.py
chuk_virtual_shell/commands/environment/alias.py
chuk_virtual_shell/commands/environment/env.py
chuk_virtual_shell/commands/environment/export.py
chuk_virtual_shell/commands/environment/unalias.py
chuk_virtual_shell/commands/filesystem/__init__.py
chuk_virtual_shell/commands/filesystem/cat.py
chuk_virtual_shell/commands/filesystem/cp.py
chuk_virtual_shell/commands/filesystem/df.py
chuk_virtual_shell/commands/filesystem/du.py
chuk_virtual_shell/commands/filesystem/echo.py
chuk_virtual_shell/commands/filesystem/find.py
chuk_virtual_shell/commands/filesystem/mkdir.py
chuk_virtual_shell/commands/filesystem/more.py
chuk_virtual_shell/commands/filesystem/mv.py
chuk_virtual_shell/commands/filesystem/quota.py
chuk_virtual_shell/commands/filesystem/rm.py
chuk_virtual_shell/commands/filesystem/rmdir.py
chuk_virtual_shell/commands/filesystem/touch.py
chuk_virtual_shell/commands/mcp/__init__.py
chuk_virtual_shell/commands/mcp/mcp_command_loader.py
chuk_virtual_shell/commands/mcp/mcp_input_formatter.py
chuk_virtual_shell/commands/mcp/mcp_output_formatter.py
chuk_virtual_shell/commands/navigation/__init__.py
chuk_virtual_shell/commands/navigation/cd.py
chuk_virtual_shell/commands/navigation/ls.py
chuk_virtual_shell/commands/navigation/pwd.py
chuk_virtual_shell/commands/navigation/tree.py
chuk_virtual_shell/commands/system/__init__.py
chuk_virtual_shell/commands/system/clear.py
chuk_virtual_shell/commands/system/date.py
chuk_virtual_shell/commands/system/exit.py
chuk_virtual_shell/commands/system/false.py
chuk_virtual_shell/commands/system/help.py
chuk_virtual_shell/commands/system/history.py
chuk_virtual_shell-0.1.7.dist-info/RECORD
