Metadata-Version: 2.1
Name: chuk-virtual-shell
Version: 0.1.7
Summary: Add your description here
Requires-Python: >=3.11
Requires-Dist: boto3>=1.40.28
Requires-Dist: chuk-mcp>=0.5.2
Requires-Dist: chuk-sessions>=0.1.0
Requires-Dist: chuk-virtual-fs>=0.1.11
Requires-Dist: pydantic>=2.11.7
Requires-Dist: pyyaml>=6.0.1
Requires-Dist: trio>=0.31.0
Provides-Extra: boto3
Requires-Dist: chuk-virtual-shell; extra == "boto3"
Provides-Extra: mcp-server
Requires-Dist: chuk-mcp-server>=0.1.0; sys_platform != "win32" and extra == "mcp-server"
